teensytoany/__init__.py
teensytoany/_static_version.py
teensytoany/_version.py
teensytoany/cli.py
teensytoany/i2c_scan.py
teensytoany/list.py
teensytoany/programmer.py
teensytoany/teensypower.py
teensytoany/teensytoany.py
teensytoany-0.14.0.dist-info/licenses/LICENSE
teensytoany-0.14.0.dist-info/METADATA
teensytoany-0.14.0.dist-info/WHEEL
teensytoany-0.14.0.dist-info/entry_points.txt
teensytoany-0.14.0.dist-info/top_level.txt
teensytoany-0.14.0.dist-info/RECORD
